odoo/addons/account_statement_import_fr_cfonb/README.rst
odoo/addons/account_statement_import_fr_cfonb/__init__.py
odoo/addons/account_statement_import_fr_cfonb/__manifest__.py
odoo/addons/account_statement_import_fr_cfonb/i18n/account_statement_import_fr_cfonb.pot
odoo/addons/account_statement_import_fr_cfonb/i18n/es.po
odoo/addons/account_statement_import_fr_cfonb/i18n/fr.po
odoo/addons/account_statement_import_fr_cfonb/i18n/nb_NO.po
odoo/addons/account_statement_import_fr_cfonb/models/__init__.py
odoo/addons/account_statement_import_fr_cfonb/models/account_journal.py
odoo/addons/account_statement_import_fr_cfonb/readme/CONTRIBUTORS.md
odoo/addons/account_statement_import_fr_cfonb/readme/DESCRIPTION.md
odoo/addons/account_statement_import_fr_cfonb/readme/USAGE.md
odoo/addons/account_statement_import_fr_cfonb/static/description/icon.png
odoo/addons/account_statement_import_fr_cfonb/static/description/index.html
odoo/addons/account_statement_import_fr_cfonb/tests/__init__.py
odoo/addons/account_statement_import_fr_cfonb/tests/test_cfonb.py
odoo/addons/account_statement_import_fr_cfonb/tests/samples/cfonb_classic.cfo
odoo/addons/account_statement_import_fr_cfonb/tests/samples/cfonb_no_carriage_return.cfo
odoo/addons/account_statement_import_fr_cfonb/views/account_statement_import.xml
odoo/addons/account_statement_import_fr_cfonb/wizard/__init__.py
odoo/addons/account_statement_import_fr_cfonb/wizard/account_statement_import.py
odoo_addon_account_statement_import_fr_cfonb-18.0.1.0.0.6.dist-info/METADATA
odoo_addon_account_statement_import_fr_cfonb-18.0.1.0.0.6.dist-info/WHEEL
odoo_addon_account_statement_import_fr_cfonb-18.0.1.0.0.6.dist-info/top_level.txt
odoo_addon_account_statement_import_fr_cfonb-18.0.1.0.0.6.dist-info/RECORD
