Metadata-Version: 2.1
Name: odoo-addon-account_statement_import_fr_cfonb
Version: 18.0.1.0.0.6
Requires-Python: >=3.10
Requires-Dist: odoo-addon-account_statement_import_file==18.0.*
Requires-Dist: odoo==18.0.*
Summary: Import CFONB bank statements files in Odoo
Home-page: https://github.com/OCA/l10n-france
License: AGPL-3
Author: Akretion,Odoo Community Association (OCA)
Author-email: support@odoo-community.org
Classifier: Programming Language :: Python
Classifier: Framework :: Odoo
Classifier: Framework :: Odoo :: 18.0
Classifier: License :: OSI Approved :: GNU Affero General Public License v3
